Metadata-Version: 2.1
Name: OmeglePy
Version: 2.3
Summary: Interact with the Omegle API
Home-page: https://github.com/isaackogan/OmeglePy
Author: Isaac Kogan
Author-email: isaacikogan@gmail.com
License: MIT
Download-URL: https://github.com/isaackogan/OmeglePy/archive/refs/tags/v_2.3.tar.gz
Keywords: OmeglePy,Omegle,Omgle-Bot,Bot
Platform: UNKNOWN
Classifier: Development Status :: 4 - Beta
Classifier: Intended Audience :: Developers
Classifier: Topic :: Communications :: Chat
Classifier: Operating System :: POSIX
Classifier: License :: OSI Approved :: MIT License
Classifier: Programming Language :: Python
Classifier: Programming Language :: Python :: 3.8
License-File: LICENSE
